nonebot_plugin_nyaturingtest/__init__.py
nonebot_plugin_nyaturingtest/client.py
nonebot_plugin_nyaturingtest/config.py
nonebot_plugin_nyaturingtest/emotion.py
nonebot_plugin_nyaturingtest/hippo_mem.py
nonebot_plugin_nyaturingtest/image_manager.py
nonebot_plugin_nyaturingtest/impression.py
nonebot_plugin_nyaturingtest/mem.py
nonebot_plugin_nyaturingtest/presets.py
nonebot_plugin_nyaturingtest/profile.py
nonebot_plugin_nyaturingtest/session.py
nonebot_plugin_nyaturingtest/vlm.py
nonebot_plugin_nyaturingtest-0.2.4.dist-info/licenses/LICENSE
nonebot_plugin_nyaturingtest-0.2.4.dist-info/METADATA
nonebot_plugin_nyaturingtest-0.2.4.dist-info/WHEEL
nonebot_plugin_nyaturingtest-0.2.4.dist-info/top_level.txt
nonebot_plugin_nyaturingtest-0.2.4.dist-info/RECORD
