Metadata-Version: 2.4
Name: nonebot-plugin-nyaturingtest
Version: 0.2.4
Summary: 也许是个有情感的聊天机器人
Author-email: shadow3aaa <shadow3aaa@gmail.com>
Project-URL: Repository, https://github.com/shadow3aaa/nonebot-plugin-nyaturingtest
Requires-Python: <3.13,>=3.10
License-File: LICENSE
Requires-Dist: nonebot2<3.0.0,>=2.4.2
Requires-Dist: nonebot-plugin-localstore<1.0.0,>=0.7.4
Requires-Dist: nonebot-plugin-uninfo<1.0.0,>=0.7.3
Requires-Dist: nonebot-adapter-onebot<3.0.0,>=2.4.6
Requires-Dist: httpx<1.0.0,>=0.27.0
Requires-Dist: openai>=1.78.1
Requires-Dist: pillow>=11.2.1
Requires-Dist: transformers>=4.51.3
Requires-Dist: anyio>=4.9.0
Requires-Dist: hipporag-nyabot>=2.0.0a2
Dynamic: license-file
